{"autoplayBgm": false, "autoplayBgs": false, "battleback1Name": "", "battleback2Name": "", "bgm": {"name": "", "pan": 0, "pitch": 100, "volume": 90}, "bgs": {"name": "", "pan": 0, "pitch": 100, "volume": 90}, "disableDashing": false, "displayName": "", "encounterList": [], "encounterStep": 30, "height": 13, "note": "", "parallaxLoopX": false, "parallaxLoopY": false, "parallaxName": "", "parallaxShow": true, "parallaxSx": 0, "parallaxSy": 0, "scrollType": 0, "specifyBattleback": false, "tilesetId": 1, "width": 17, "data": [0, 0, 0, 0, 0, 0, 0, 0, 0, 0, 0, 0, 0, 0, 0, 0, 0, 0, 0, 0, 0, 0, 0, 0, 0, 0, 0, 0, 0, 0, 0, 0, 0, 0, 0, 0, 0, 0, 0, 0, 0, 0, 0, 0, 0, 0, 0, 0, 0, 0, 0, 0, 0, 0, 0, 0, 0, 0, 0, 0, 0, 0, 0, 0, 0, 0, 0, 0, 0, 0, 0, 0, 0, 0, 0, 0, 0, 0, 0, 0, 0, 0, 0, 0, 0, 0, 0, 0, 0, 0, 0, 0, 0, 0, 0, 0, 0, 0, 0, 0, 0, 0, 0, 0, 0, 0, 0, 0, 0, 0, 0, 0, 0, 0, 0, 0, 0, 0, 0, 0, 0, 0, 0, 0, 0, 0, 0, 0, 0, 0, 0, 0, 0, 0, 0, 0, 0, 0, 0, 0, 0, 0, 0, 0, 0, 0, 0, 0, 0, 0, 0, 0, 0, 0, 0, 0, 0, 0, 0, 0, 0, 0, 0, 0, 0, 0, 0, 0, 0, 0, 0, 0, 0, 0, 0, 0, 0, 0, 0, 0, 0, 0, 0, 0, 0, 0, 0, 0, 0, 0, 0, 0, 0, 0, 0, 0, 0, 0, 0, 0, 0, 0, 0, 0, 0, 0, 0, 0, 0, 0, 0, 0, 0, 0, 0, 0, 0, 0, 0, 0, 0, 0, 0, 0, 0, 0, 0, 0, 0, 0, 0, 0, 0, 0, 0, 0, 0, 0, 0, 0, 0, 0, 0, 0, 0, 0, 0, 0, 0, 0, 0, 0, 0, 0, 0, 0, 0, 0, 0, 0, 0, 0, 0, 0, 0, 0, 0, 0, 0, 0, 0, 0, 0, 0, 0, 0, 0, 0, 0, 0, 0, 0, 0, 0, 0, 0, 0, 0, 0, 0, 0, 0, 0, 0, 0, 0, 0, 0, 0, 0, 0, 0, 0, 0, 0, 0, 0, 0, 0, 0, 0, 0, 0, 0, 0, 0, 0, 0, 0, 0, 0, 0, 0, 0, 0, 0, 0, 0, 0, 0, 0, 0, 0, 0, 0, 0, 0, 0, 0, 0, 0, 0, 0, 0, 0, 0, 0, 0, 0, 0, 0, 0, 0, 0, 0, 0, 0, 0, 0, 0, 0, 0, 0, 0, 0, 0, 0, 0, 0, 0, 0, 0, 0, 0, 0, 0, 0, 0, 0, 0, 0, 0, 0, 0, 0, 0, 0, 0, 0, 0, 0, 0, 0, 0, 0, 0, 0, 0, 0, 0, 0, 0, 0, 0, 0, 0, 0, 0, 0, 0, 0, 0, 0, 0, 0, 0, 0, 0, 0, 0, 0, 0, 0, 0, 0, 0, 0, 0, 0, 0, 0, 0, 0, 0, 0, 0, 0, 0, 0, 0, 0, 0, 0, 0, 0, 0, 0, 0, 0, 0, 0, 0, 0, 0, 0, 0, 0, 0, 0, 0, 0, 0, 0, 0, 0, 0, 0, 0, 0, 0, 0, 0, 0, 0, 0, 0, 0, 0, 0, 0, 0, 0, 0, 0, 0, 0, 0, 0, 0, 0, 0, 0, 0, 0, 0, 0, 0, 0, 0, 0, 0, 0, 0, 0, 0, 0, 0, 0, 0, 0, 0, 0, 0, 0, 0, 0, 0, 0, 0, 0, 0, 0, 0, 0, 0, 0, 0, 0, 0, 0, 0, 0, 0, 0, 0, 0, 0, 0, 0, 0, 0, 0, 0, 0, 0, 0, 0, 0, 0, 0, 0, 0, 0, 0, 0, 0, 0, 0, 0, 0, 0, 0, 0, 0, 0, 0, 0, 0, 0, 0, 0, 0, 0, 0, 0, 0, 0, 0, 0, 0, 0, 0, 0, 0, 0, 0, 0, 0, 0, 0, 0, 0, 0, 0, 0, 0, 0, 0, 0, 0, 0, 0, 0, 0, 0, 0, 0, 0, 0, 0, 0, 0, 0, 0, 0, 0, 0, 0, 0, 0, 0, 0, 0, 0, 0, 0, 0, 0, 0, 0, 0, 0, 0, 0, 0, 0, 0, 0, 0, 0, 0, 0, 0, 0, 0, 0, 0, 0, 0, 0, 0, 0, 0, 0, 0, 0, 0, 0, 0, 0, 0, 0, 0, 0, 0, 0, 0, 0, 0, 0, 0, 0, 0, 0, 0, 0, 0, 0, 0, 0, 0, 0, 0, 0, 0, 0, 0, 0, 0, 0, 0, 0, 0, 0, 0, 0, 0, 0, 0, 0, 0, 0, 0, 0, 0, 0, 0, 0, 0, 0, 0, 0, 0, 0, 0, 0, 0, 0, 0, 0, 0, 0, 0, 0, 0, 0, 0, 0, 0, 0, 0, 0, 0, 0, 0, 0, 0, 0, 0, 0, 0, 0, 0, 0, 0, 0, 0, 0, 0, 0, 0, 0, 0, 0, 0, 0, 0, 0, 0, 0, 0, 0, 0, 0, 0, 0, 0, 0, 0, 0, 0, 0, 0, 0, 0, 0, 0, 0, 0, 0, 0, 0, 0, 0, 0, 0, 0, 0, 0, 0, 0, 0, 0, 0, 0, 0, 0, 0, 0, 0, 0, 0, 0, 0, 0, 0, 0, 0, 0, 0, 0, 0, 0, 0, 0, 0, 0, 0, 0, 0, 0, 0, 0, 0, 0, 0, 0, 0, 0, 0, 0, 0, 0, 0, 0, 0, 0, 0, 0, 0, 0, 0, 0, 0, 0, 0, 0, 0, 0, 0, 0, 0, 0, 0, 0, 0, 0, 0, 0, 0, 0, 0, 0, 0, 0, 0, 0, 0, 0, 0, 0, 0, 0, 0, 0, 0, 0, 0, 0, 0, 0, 0, 0, 0, 0, 0, 0, 0, 0, 0, 0, 0, 0, 0, 0, 0, 0, 0, 0, 0, 0, 0, 0, 0, 0, 0, 0, 0, 0, 0, 0, 0, 0, 0, 0, 0, 0, 0, 0, 0, 0, 0, 0, 0, 0, 0, 0, 0, 0, 0, 0, 0, 0, 0, 0, 0, 0, 0, 0, 0, 0, 0, 0, 0, 0, 0, 0, 0, 0, 0, 0, 0, 0, 0, 0, 0, 0, 0, 0, 0, 0, 0, 0, 0, 0, 0, 0, 0, 0, 0, 0, 0, 0, 0, 0, 0, 0, 0, 0, 0, 0, 0, 0, 0, 0, 0, 0, 0, 0, 0, 0, 0, 0, 0, 0, 0, 0, 0, 0, 0, 0, 0, 0, 0, 0, 0, 0, 0, 0, 0, 0, 0, 0, 0, 0, 0, 0, 0, 0, 0, 0, 0, 0, 0, 0, 0, 0, 0, 0, 0, 0, 0, 0, 0, 0, 0, 0, 0, 0, 0, 0, 0, 0, 0, 0, 0, 0, 0, 0, 0, 0, 0, 0, 0, 0, 0, 0, 0, 0, 0, 0, 0, 0, 0, 0, 0, 0, 0, 0, 0, 0, 0, 0, 0, 0, 0, 0, 0, 0, 0, 0, 0, 0, 0, 0, 0, 0, 0, 0, 0, 0, 0, 0, 0, 0, 0, 0, 0, 0, 0, 0, 0, 0, 0, 0, 0, 0, 0, 0, 0, 0, 0, 0, 0, 0, 0, 0, 0, 0, 0, 0, 0, 0, 0, 0, 0, 0, 0, 0, 0, 0, 0, 0, 0, 0, 0, 0, 0, 0, 0, 0, 0, 0, 0, 0, 0, 0, 0, 0, 0, 0, 0, 0, 0, 0, 0, 0, 0, 0, 0, 0, 0, 0, 0, 0, 0, 0, 0, 0, 0, 0, 0, 0, 0, 0, 0, 0, 0, 0, 0, 0, 0, 0, 0, 0, 0, 0, 0, 0, 0, 0, 0, 0, 0, 0, 0, 0, 0, 0, 0, 0, 0, 0, 0, 0, 0, 0, 0, 0, 0, 0, 0, 0, 0, 0, 0, 0, 0, 0, 0, 0, 0, 0, 0, 0, 0, 0, 0, 0, 0, 0, 0, 0, 0, 0, 0, 0, 0, 0, 0, 0, 0, 0, 0, 0, 0, 0, 0, 0, 0, 0, 0, 0, 0, 0, 0, 0, 0, 0, 0, 0, 0, 0, 0, 0, 0, 0, 0, 0, 0, 0, 0, 0, 0, 0, 0, 0, 0, 0, 0, 0, 0, 0, 0, 0, 0, 0, 0, 0, 0, 0, 0, 0, 0, 0, 0, 0, 0, 0, 0, 0, 0, 0, 0, 0, 0, 0, 0, 0, 0, 0, 0, 0, 0, 0, 0, 0, 0, 0, 0, 0, 0, 0, 0, 0, 0], "events": [null, {"id": 1, "name": "EV001", "note": "", "pages": [{"conditions": {"actorId": 1, "actorValid": false, "itemId": 1, "itemValid": false, "selfSwitchCh": "A", "selfSwitchValid": false, "switch1Id": 1, "switch1Valid": false, "switch2Id": 1, "switch2Valid": false, "variableId": 1, "variableValid": false, "variableValue": 0}, "directionFix": false, "image": {"characterIndex": 0, "characterName": "", "direction": 2, "pattern": 0, "tileId": 0}, "list": [{"code": 231, "indent": 0, "parameters": [70, "blackscreen", 0, 0, 0, 0, 100, 100, 255, 0]}, {"code": 122, "indent": 0, "parameters": [1816, 1816, 0, 0, 0]}, {"code": 230, "indent": 0, "parameters": [10]}, {"code": 108, "indent": 0, "parameters": ["KARIN"]}, {"code": 111, "indent": 0, "parameters": [1, 1389, 0, 0, 0]}, {"code": 111, "indent": 1, "parameters": [0, 2404, 1]}, {"code": 111, "indent": 2, "parameters": [0, 3433, 1]}, {"code": 111, "indent": 3, "parameters": [0, 4580, 1]}, {"code": 111, "indent": 4, "parameters": [1, 2548, 0, 0, 0]}, {"code": 231, "indent": 5, "parameters": [57, "train_karin", 0, 0, 513, 168, 100, 100, 255, 0]}, {"code": 122, "indent": 5, "parameters": [1816, 1816, 1, 0, 1]}, {"code": 0, "indent": 5, "parameters": []}, {"code": 412, "indent": 4, "parameters": []}, {"code": 0, "indent": 4, "parameters": []}, {"code": 412, "indent": 3, "parameters": []}, {"code": 0, "indent": 3, "parameters": []}, {"code": 412, "indent": 2, "parameters": []}, {"code": 0, "indent": 2, "parameters": []}, {"code": 412, "indent": 1, "parameters": []}, {"code": 108, "indent": 1, "parameters": ["OSAA"]}, {"code": 111, "indent": 1, "parameters": [0, 2401, 1]}, {"code": 111, "indent": 2, "parameters": [0, 3774, 1]}, {"code": 111, "indent": 3, "parameters": [0, 3814, 1]}, {"code": 111, "indent": 4, "parameters": [1, 2545, 0, 0, 0]}, {"code": 231, "indent": 5, "parameters": [62, "train_osaa", 0, 0, 590, 180, 100, 100, 255, 0]}, {"code": 122, "indent": 5, "parameters": [1816, 1816, 1, 0, 1]}, {"code": 0, "indent": 5, "parameters": []}, {"code": 412, "indent": 4, "parameters": []}, {"code": 0, "indent": 4, "parameters": []}, {"code": 412, "indent": 3, "parameters": []}, {"code": 0, "indent": 3, "parameters": []}, {"code": 412, "indent": 2, "parameters": []}, {"code": 0, "indent": 2, "parameters": []}, {"code": 412, "indent": 1, "parameters": []}, {"code": 108, "indent": 1, "parameters": ["OLIVIA"]}, {"code": 111, "indent": 1, "parameters": [0, 2402, 1]}, {"code": 111, "indent": 2, "parameters": [0, 2695, 1]}, {"code": 111, "indent": 3, "parameters": [0, 4751, 1]}, {"code": 111, "indent": 4, "parameters": [1, 2546, 0, 0, 0]}, {"code": 231, "indent": 5, "parameters": [60, "train_olivia", 0, 0, 164, 290, 100, 100, 255, 0]}, {"code": 122, "indent": 5, "parameters": [1816, 1816, 1, 0, 1]}, {"code": 0, "indent": 5, "parameters": []}, {"code": 412, "indent": 4, "parameters": []}, {"code": 0, "indent": 4, "parameters": []}, {"code": 412, "indent": 3, "parameters": []}, {"code": 0, "indent": 3, "parameters": []}, {"code": 412, "indent": 2, "parameters": []}, {"code": 0, "indent": 2, "parameters": []}, {"code": 412, "indent": 1, "parameters": []}, {"code": 108, "indent": 1, "parameters": ["MARCOH"]}, {"code": 111, "indent": 1, "parameters": [0, 2403, 1]}, {"code": 111, "indent": 2, "parameters": [0, 2676, 1]}, {"code": 111, "indent": 3, "parameters": [0, 2791, 1]}, {"code": 111, "indent": 4, "parameters": [1, 2547, 0, 0, 0]}, {"code": 231, "indent": 5, "parameters": [63, "train_marcoh", 0, 0, 652, 229, 100, 100, 255, 0]}, {"code": 122, "indent": 5, "parameters": [1816, 1816, 1, 0, 1]}, {"code": 0, "indent": 5, "parameters": []}, {"code": 412, "indent": 4, "parameters": []}, {"code": 0, "indent": 4, "parameters": []}, {"code": 412, "indent": 3, "parameters": []}, {"code": 0, "indent": 3, "parameters": []}, {"code": 412, "indent": 2, "parameters": []}, {"code": 0, "indent": 2, "parameters": []}, {"code": 412, "indent": 1, "parameters": []}, {"code": 108, "indent": 1, "parameters": ["DAAN"]}, {"code": 111, "indent": 1, "parameters": [0, 243, 1]}, {"code": 111, "indent": 2, "parameters": [0, 2815, 1]}, {"code": 111, "indent": 3, "parameters": [0, 4752, 1]}, {"code": 111, "indent": 4, "parameters": [1, 2543, 0, 0, 0]}, {"code": 231, "indent": 5, "parameters": [55, "train_daan", 0, 0, 224, 169, 100, 100, 255, 0]}, {"code": 122, "indent": 5, "parameters": [1816, 1816, 1, 0, 1]}, {"code": 0, "indent": 5, "parameters": []}, {"code": 412, "indent": 4, "parameters": []}, {"code": 0, "indent": 4, "parameters": []}, {"code": 412, "indent": 3, "parameters": []}, {"code": 0, "indent": 3, "parameters": []}, {"code": 412, "indent": 2, "parameters": []}, {"code": 0, "indent": 2, "parameters": []}, {"code": 412, "indent": 1, "parameters": []}, {"code": 108, "indent": 1, "parameters": ["ABELLA"]}, {"code": 111, "indent": 1, "parameters": [0, 244, 1]}, {"code": 111, "indent": 2, "parameters": [0, 2637, 1]}, {"code": 111, "indent": 3, "parameters": [0, 2657, 1]}, {"code": 111, "indent": 4, "parameters": [1, 2544, 0, 0, 0]}, {"code": 231, "indent": 5, "parameters": [58, "train_abella", 0, 0, 84, 189, 100, 100, 255, 0]}, {"code": 122, "indent": 5, "parameters": [1816, 1816, 1, 0, 1]}, {"code": 0, "indent": 5, "parameters": []}, {"code": 412, "indent": 4, "parameters": []}, {"code": 0, "indent": 4, "parameters": []}, {"code": 412, "indent": 3, "parameters": []}, {"code": 0, "indent": 3, "parameters": []}, {"code": 412, "indent": 2, "parameters": []}, {"code": 0, "indent": 2, "parameters": []}, {"code": 412, "indent": 1, "parameters": []}, {"code": 108, "indent": 1, "parameters": ["LEVI"]}, {"code": 111, "indent": 1, "parameters": [0, 246, 1]}, {"code": 111, "indent": 2, "parameters": [0, 3485, 1]}, {"code": 111, "indent": 3, "parameters": [0, 3539, 1]}, {"code": 111, "indent": 4, "parameters": [1, 2541, 0, 0, 0]}, {"code": 231, "indent": 5, "parameters": [54, "train_levi", 0, 0, 343, 190, 100, 100, 255, 0]}, {"code": 122, "indent": 5, "parameters": [1816, 1816, 1, 0, 1]}, {"code": 0, "indent": 5, "parameters": []}, {"code": 412, "indent": 4, "parameters": []}, {"code": 0, "indent": 4, "parameters": []}, {"code": 412, "indent": 3, "parameters": []}, {"code": 0, "indent": 3, "parameters": []}, {"code": 412, "indent": 2, "parameters": []}, {"code": 0, "indent": 2, "parameters": []}, {"code": 412, "indent": 1, "parameters": []}, {"code": 108, "indent": 1, "parameters": ["MARINA"]}, {"code": 111, "indent": 1, "parameters": [0, 242, 1]}, {"code": 111, "indent": 2, "parameters": [0, 3552, 1]}, {"code": 111, "indent": 3, "parameters": [0, 1520, 1]}, {"code": 111, "indent": 4, "parameters": [1, 2542, 0, 0, 0]}, {"code": 231, "indent": 5, "parameters": [61, "train_marina", 0, 0, 448, 186, 100, 100, 255, 0]}, {"code": 122, "indent": 5, "parameters": [1816, 1816, 1, 0, 1]}, {"code": 0, "indent": 5, "parameters": []}, {"code": 412, "indent": 4, "parameters": []}, {"code": 0, "indent": 4, "parameters": []}, {"code": 412, "indent": 3, "parameters": []}, {"code": 0, "indent": 3, "parameters": []}, {"code": 412, "indent": 2, "parameters": []}, {"code": 0, "indent": 2, "parameters": []}, {"code": 412, "indent": 1, "parameters": []}, {"code": 108, "indent": 1, "parameters": ["PAV"]}, {"code": 111, "indent": 1, "parameters": [0, 2410, 1]}, {"code": 111, "indent": 2, "parameters": [0, 2729, 1]}, {"code": 231, "indent": 3, "parameters": [53, "train_pav", 0, 0, 400, 90, 100, 100, 255, 0]}, {"code": 122, "indent": 3, "parameters": [1816, 1816, 1, 0, 1]}, {"code": 0, "indent": 3, "parameters": []}, {"code": 412, "indent": 2, "parameters": []}, {"code": 0, "indent": 2, "parameters": []}, {"code": 412, "indent": 1, "parameters": []}, {"code": 108, "indent": 1, "parameters": ["AUGUST"]}, {"code": 111, "indent": 1, "parameters": [0, 2407, 1]}, {"code": 111, "indent": 2, "parameters": [0, 4243, 1]}, {"code": 111, "indent": 3, "parameters": [0, 4578, 1]}, {"code": 231, "indent": 4, "parameters": [51, "train_august", 0, 0, 551, 119, 100, 100, 255, 0]}, {"code": 122, "indent": 4, "parameters": [1816, 1816, 1, 0, 1]}, {"code": 0, "indent": 4, "parameters": []}, {"code": 412, "indent": 3, "parameters": []}, {"code": 0, "indent": 3, "parameters": []}, {"code": 412, "indent": 2, "parameters": []}, {"code": 0, "indent": 2, "parameters": []}, {"code": 412, "indent": 1, "parameters": []}, {"code": 108, "indent": 1, "parameters": ["CALIGURA"]}, {"code": 111, "indent": 1, "parameters": [0, 2408, 1]}, {"code": 111, "indent": 2, "parameters": [0, 3401, 1]}, {"code": 111, "indent": 3, "parameters": [0, 4551, 1]}, {"code": 231, "indent": 4, "parameters": [52, "train_caligura", 0, 0, 317, 129, 100, 100, 255, 0]}, {"code": 122, "indent": 4, "parameters": [1816, 1816, 1, 0, 1]}, {"code": 0, "indent": 4, "parameters": []}, {"code": 412, "indent": 3, "parameters": []}, {"code": 0, "indent": 3, "parameters": []}, {"code": 412, "indent": 2, "parameters": []}, {"code": 0, "indent": 2, "parameters": []}, {"code": 412, "indent": 1, "parameters": []}, {"code": 108, "indent": 1, "parameters": ["SAMARIE"]}, {"code": 111, "indent": 1, "parameters": [0, 2406, 1]}, {"code": 111, "indent": 2, "parameters": [0, 3681, 1]}, {"code": 111, "indent": 3, "parameters": [0, 5000, 1]}, {"code": 231, "indent": 4, "parameters": [56, "train_samarie", 0, 0, 438, 153, 100, 100, 255, 0]}, {"code": 122, "indent": 4, "parameters": [1816, 1816, 1, 0, 1]}, {"code": 0, "indent": 4, "parameters": []}, {"code": 412, "indent": 3, "parameters": []}, {"code": 0, "indent": 3, "parameters": []}, {"code": 412, "indent": 2, "parameters": []}, {"code": 0, "indent": 2, "parameters": []}, {"code": 412, "indent": 1, "parameters": []}, {"code": 108, "indent": 1, "parameters": ["HENRYK"]}, {"code": 111, "indent": 1, "parameters": [0, 2409, 1]}, {"code": 111, "indent": 2, "parameters": [0, 2626, 1]}, {"code": 111, "indent": 3, "parameters": [0, 4716, 1]}, {"code": 231, "indent": 4, "parameters": [59, "train_henryk", 0, 0, 2, 199, 100, 100, 255, 0]}, {"code": 122, "indent": 4, "parameters": [1816, 1816, 1, 0, 1]}, {"code": 0, "indent": 4, "parameters": []}, {"code": 412, "indent": 3, "parameters": []}, {"code": 0, "indent": 3, "parameters": []}, {"code": 412, "indent": 2, "parameters": []}, {"code": 0, "indent": 2, "parameters": []}, {"code": 412, "indent": 1, "parameters": []}, {"code": 108, "indent": 1, "parameters": ["TANAKA"]}, {"code": 111, "indent": 1, "parameters": [0, 2405, 1]}, {"code": 111, "indent": 2, "parameters": [0, 2685, 1]}, {"code": 111, "indent": 3, "parameters": [0, 2774, 1]}, {"code": 231, "indent": 4, "parameters": [64, "train_tanaka", 0, 0, 713, 243, 100, 100, 255, 0]}, {"code": 122, "indent": 4, "parameters": [1816, 1816, 1, 0, 1]}, {"code": 0, "indent": 4, "parameters": []}, {"code": 412, "indent": 3, "parameters": []}, {"code": 0, "indent": 3, "parameters": []}, {"code": 412, "indent": 2, "parameters": []}, {"code": 0, "indent": 2, "parameters": []}, {"code": 412, "indent": 1, "parameters": []}, {"code": 0, "indent": 1, "parameters": []}, {"code": 411, "indent": 0, "parameters": []}, {"code": 0, "indent": 1, "parameters": []}, {"code": 412, "indent": 0, "parameters": []}, {"code": 231, "indent": 0, "parameters": [50, "train_ending", 0, 0, -135, 0, 100, 100, 255, 0]}, {"code": 232, "indent": 0, "parameters": [70, 0, 0, 0, 0, 0, 100, 100, 0, 0, 130, true]}, {"code": 230, "indent": 0, "parameters": [60]}, {"code": 111, "indent": 0, "parameters": [1, 1816, 0, 0, 0]}, {"code": 101, "indent": 1, "parameters": ["", 0, 1, 2]}, {"code": 401, "indent": 1, "parameters": ["Ни одна душа не вернулась из этого путешествия..."]}, {"code": 0, "indent": 1, "parameters": []}, {"code": 411, "indent": 0, "parameters": []}, {"code": 111, "indent": 1, "parameters": [1, 1816, 0, 1, 3]}, {"code": 101, "indent": 2, "parameters": ["", 0, 1, 2]}, {"code": 401, "indent": 2, "parameters": ["\\c[2]\\v[1816]\\c[0] сумел пережить все ужасы..."]}, {"code": 0, "indent": 2, "parameters": []}, {"code": 411, "indent": 1, "parameters": []}, {"code": 101, "indent": 2, "parameters": ["", 0, 1, 2]}, {"code": 401, "indent": 2, "parameters": ["Только \\c[2]1\\c[0] удалось пережить все ужасы..."]}, {"code": 0, "indent": 2, "parameters": []}, {"code": 412, "indent": 1, "parameters": []}, {"code": 0, "indent": 1, "parameters": []}, {"code": 412, "indent": 0, "parameters": []}, {"code": 230, "indent": 0, "parameters": [100]}, {"code": 111, "indent": 0, "parameters": [13, 0]}, {"code": 232, "indent": 1, "parameters": [70, 0, 0, 0, 0, 0, 100, 100, 255, 0, 130, true]}, {"code": 0, "indent": 1, "parameters": []}, {"code": 412, "indent": 0, "parameters": []}, {"code": 230, "indent": 0, "parameters": [40]}, {"code": 123, "indent": 0, "parameters": ["A", 0]}, {"code": 0, "indent": 0, "parameters": []}], "moveFrequency": 3, "moveRoute": {"list": [{"code": 0, "parameters": []}], "repeat": true, "skippable": false, "wait": false}, "moveSpeed": 3, "moveType": 0, "priorityType": 0, "stepAnime": false, "through": false, "trigger": 3, "walkAnime": true}, {"conditions": {"actorId": 1, "actorValid": false, "itemId": 1, "itemValid": false, "selfSwitchCh": "D", "selfSwitchValid": false, "switch1Id": 1, "switch1Valid": false, "switch2Id": 1, "switch2Valid": false, "variableId": 1388, "variableValid": true, "variableValue": 1}, "directionFix": false, "image": {"characterIndex": 0, "characterName": "", "direction": 2, "pattern": 0, "tileId": 0}, "list": [{"code": 231, "indent": 0, "parameters": [70, "blackscreen", 0, 0, 0, 0, 100, 100, 255, 0]}, {"code": 122, "indent": 0, "parameters": [1816, 1816, 0, 0, 0]}, {"code": 230, "indent": 0, "parameters": [10]}, {"code": 108, "indent": 0, "parameters": ["KARIN"]}, {"code": 111, "indent": 0, "parameters": [0, 2404, 0]}, {"code": 231, "indent": 1, "parameters": [57, "train_karin", 0, 0, 513, 168, 100, 100, 255, 0]}, {"code": 0, "indent": 1, "parameters": []}, {"code": 412, "indent": 0, "parameters": []}, {"code": 108, "indent": 0, "parameters": ["OSAA"]}, {"code": 111, "indent": 0, "parameters": [0, 2401, 0]}, {"code": 231, "indent": 1, "parameters": [62, "train_osaa", 0, 0, 590, 180, 100, 100, 255, 0]}, {"code": 0, "indent": 1, "parameters": []}, {"code": 412, "indent": 0, "parameters": []}, {"code": 108, "indent": 0, "parameters": ["OLIVIA"]}, {"code": 111, "indent": 0, "parameters": [0, 2402, 0]}, {"code": 231, "indent": 1, "parameters": [60, "train_olivia", 0, 0, 164, 290, 100, 100, 255, 0]}, {"code": 0, "indent": 1, "parameters": []}, {"code": 412, "indent": 0, "parameters": []}, {"code": 108, "indent": 0, "parameters": ["MARCOH"]}, {"code": 111, "indent": 0, "parameters": [0, 2403, 0]}, {"code": 231, "indent": 1, "parameters": [63, "train_marcoh", 0, 0, 652, 229, 100, 100, 255, 0]}, {"code": 0, "indent": 1, "parameters": []}, {"code": 412, "indent": 0, "parameters": []}, {"code": 108, "indent": 0, "parameters": ["DAAN"]}, {"code": 111, "indent": 0, "parameters": [0, 243, 0]}, {"code": 231, "indent": 1, "parameters": [55, "train_daan", 0, 0, 224, 169, 100, 100, 255, 0]}, {"code": 0, "indent": 1, "parameters": []}, {"code": 412, "indent": 0, "parameters": []}, {"code": 108, "indent": 0, "parameters": ["ABELLA"]}, {"code": 111, "indent": 0, "parameters": [0, 244, 0]}, {"code": 231, "indent": 1, "parameters": [58, "train_abella", 0, 0, 84, 189, 100, 100, 255, 0]}, {"code": 0, "indent": 1, "parameters": []}, {"code": 412, "indent": 0, "parameters": []}, {"code": 108, "indent": 0, "parameters": ["LEVI"]}, {"code": 111, "indent": 0, "parameters": [0, 246, 0]}, {"code": 231, "indent": 1, "parameters": [54, "train_levi", 0, 0, 343, 190, 100, 100, 255, 0]}, {"code": 0, "indent": 1, "parameters": []}, {"code": 412, "indent": 0, "parameters": []}, {"code": 108, "indent": 0, "parameters": ["MARINA"]}, {"code": 111, "indent": 0, "parameters": [0, 242, 0]}, {"code": 231, "indent": 1, "parameters": [61, "train_marina", 0, 0, 448, 186, 100, 100, 255, 0]}, {"code": 0, "indent": 1, "parameters": []}, {"code": 412, "indent": 0, "parameters": []}, {"code": 108, "indent": 0, "parameters": ["PAV"]}, {"code": 111, "indent": 0, "parameters": [0, 2410, 0]}, {"code": 231, "indent": 1, "parameters": [53, "train_pav", 0, 0, 400, 90, 100, 100, 255, 0]}, {"code": 0, "indent": 1, "parameters": []}, {"code": 412, "indent": 0, "parameters": []}, {"code": 108, "indent": 0, "parameters": ["AUGUST"]}, {"code": 111, "indent": 0, "parameters": [0, 2407, 0]}, {"code": 231, "indent": 1, "parameters": [51, "train_august", 0, 0, 551, 119, 100, 100, 255, 0]}, {"code": 0, "indent": 1, "parameters": []}, {"code": 412, "indent": 0, "parameters": []}, {"code": 108, "indent": 0, "parameters": ["CALIGURA"]}, {"code": 111, "indent": 0, "parameters": [0, 2408, 0]}, {"code": 231, "indent": 1, "parameters": [52, "train_caligura", 0, 0, 317, 129, 100, 100, 255, 0]}, {"code": 0, "indent": 1, "parameters": []}, {"code": 412, "indent": 0, "parameters": []}, {"code": 108, "indent": 0, "parameters": ["SAMARIE"]}, {"code": 111, "indent": 0, "parameters": [0, 2406, 0]}, {"code": 231, "indent": 1, "parameters": [56, "train_samarie", 0, 0, 438, 153, 100, 100, 255, 0]}, {"code": 0, "indent": 1, "parameters": []}, {"code": 412, "indent": 0, "parameters": []}, {"code": 108, "indent": 0, "parameters": ["HENRYK"]}, {"code": 111, "indent": 0, "parameters": [0, 2409, 0]}, {"code": 231, "indent": 1, "parameters": [59, "train_henryk", 0, 0, 2, 199, 100, 100, 255, 0]}, {"code": 0, "indent": 1, "parameters": []}, {"code": 412, "indent": 0, "parameters": []}, {"code": 108, "indent": 0, "parameters": ["TANAKA"]}, {"code": 111, "indent": 0, "parameters": [0, 2405, 0]}, {"code": 231, "indent": 1, "parameters": [64, "train_tanaka", 0, 0, 713, 243, 100, 100, 255, 0]}, {"code": 0, "indent": 1, "parameters": []}, {"code": 412, "indent": 0, "parameters": []}, {"code": 231, "indent": 0, "parameters": [50, "train_ending", 0, 0, -135, 0, 100, 100, 255, 0]}, {"code": 232, "indent": 0, "parameters": [70, 0, 0, 0, 0, 0, 100, 100, 0, 0, 160, true]}, {"code": 230, "indent": 0, "parameters": [60]}, {"code": 101, "indent": 0, "parameters": ["", 0, 1, 2]}, {"code": 401, "indent": 0, "parameters": ["Единственной душой, которая вернулась из путешествия, были вы..."]}, {"code": 230, "indent": 0, "parameters": [100]}, {"code": 111, "indent": 0, "parameters": [13, 0]}, {"code": 232, "indent": 1, "parameters": [70, 0, 0, 0, 0, 0, 100, 100, 255, 0, 150, true]}, {"code": 230, "indent": 1, "parameters": [40]}, {"code": 0, "indent": 1, "parameters": []}, {"code": 412, "indent": 0, "parameters": []}, {"code": 231, "indent": 0, "parameters": [66, "book_photo", 0, 0, 32, 5, 90, 90, 0, 0]}, {"code": 111, "indent": 0, "parameters": [0, 246, 0]}, {"code": 231, "indent": 1, "parameters": [67, "ending_exsoldier", 0, 0, 105, -55, 100, 100, 0, 0]}, {"code": 121, "indent": 1, "parameters": [1428, 1428, 0]}, {"code": 0, "indent": 1, "parameters": []}, {"code": 411, "indent": 0, "parameters": []}, {"code": 111, "indent": 1, "parameters": [0, 242, 0]}, {"code": 231, "indent": 2, "parameters": [67, "ending_occultist", 0, 0, 0, 0, 100, 100, 0, 0]}, {"code": 121, "indent": 2, "parameters": [1429, 1429, 0]}, {"code": 0, "indent": 2, "parameters": []}, {"code": 411, "indent": 1, "parameters": []}, {"code": 111, "indent": 2, "parameters": [0, 243, 0]}, {"code": 231, "indent": 3, "parameters": [67, "ending_doctor", 0, 0, 0, 0, 100, 100, 0, 0]}, {"code": 121, "indent": 3, "parameters": [1430, 1430, 0]}, {"code": 0, "indent": 3, "parameters": []}, {"code": 411, "indent": 2, "parameters": []}, {"code": 111, "indent": 3, "parameters": [0, 244, 0]}, {"code": 231, "indent": 4, "parameters": [67, "ending_mechanic", 0, 0, 0, 0, 100, 100, 0, 0]}, {"code": 121, "indent": 4, "parameters": [1431, 1431, 0]}, {"code": 0, "indent": 4, "parameters": []}, {"code": 411, "indent": 3, "parameters": []}, {"code": 111, "indent": 4, "parameters": [0, 2401, 0]}, {"code": 231, "indent": 5, "parameters": [67, "ending_yellowmage", 0, 0, 0, 0, 100, 100, 0, 0]}, {"code": 121, "indent": 5, "parameters": [1432, 1432, 0]}, {"code": 0, "indent": 5, "parameters": []}, {"code": 411, "indent": 4, "parameters": []}, {"code": 111, "indent": 5, "parameters": [0, 2402, 0]}, {"code": 231, "indent": 6, "parameters": [67, "ending_botanist", 0, 0, 0, 0, 100, 100, 0, 0]}, {"code": 121, "indent": 6, "parameters": [1433, 1433, 0]}, {"code": 0, "indent": 6, "parameters": []}, {"code": 411, "indent": 5, "parameters": []}, {"code": 111, "indent": 6, "parameters": [0, 2403, 0]}, {"code": 231, "indent": 7, "parameters": [67, "ending_thug", 0, 0, 0, 0, 100, 100, 0, 0]}, {"code": 121, "indent": 7, "parameters": [1434, 1434, 0]}, {"code": 0, "indent": 7, "parameters": []}, {"code": 411, "indent": 6, "parameters": []}, {"code": 111, "indent": 7, "parameters": [0, 2404, 0]}, {"code": 231, "indent": 8, "parameters": [67, "ending_journalist", 0, 0, 0, 0, 100, 100, 0, 0]}, {"code": 121, "indent": 8, "parameters": [1435, 1435, 0]}, {"code": 0, "indent": 8, "parameters": []}, {"code": 411, "indent": 7, "parameters": []}, {"code": 0, "indent": 8, "parameters": []}, {"code": 412, "indent": 7, "parameters": []}, {"code": 0, "indent": 7, "parameters": []}, {"code": 412, "indent": 6, "parameters": []}, {"code": 0, "indent": 6, "parameters": []}, {"code": 412, "indent": 5, "parameters": []}, {"code": 0, "indent": 5, "parameters": []}, {"code": 412, "indent": 4, "parameters": []}, {"code": 0, "indent": 4, "parameters": []}, {"code": 412, "indent": 3, "parameters": []}, {"code": 0, "indent": 3, "parameters": []}, {"code": 412, "indent": 2, "parameters": []}, {"code": 0, "indent": 2, "parameters": []}, {"code": 412, "indent": 1, "parameters": []}, {"code": 0, "indent": 1, "parameters": []}, {"code": 412, "indent": 0, "parameters": []}, {"code": 111, "indent": 0, "parameters": [13, 0]}, {"code": 231, "indent": 1, "parameters": [65, "blackscreen", 0, 0, 0, 0, 100, 100, 0, 0]}, {"code": 230, "indent": 1, "parameters": [5]}, {"code": 232, "indent": 1, "parameters": [65, 0, 0, 0, 0, 0, 100, 100, 130, 0, 60, true]}, {"code": 0, "indent": 1, "parameters": []}, {"code": 412, "indent": 0, "parameters": []}, {"code": 250, "indent": 0, "parameters": [{"name": "fnh_book1", "volume": 90, "pitch": 100, "pan": 0}]}, {"code": 232, "indent": 0, "parameters": [66, 0, 0, 0, 32, 10, 90, 90, 255, 0, 60, false]}, {"code": 230, "indent": 0, "parameters": [25]}, {"code": 250, "indent": 0, "parameters": [{"name": "fnh_book1", "volume": 90, "pitch": 150, "pan": 0}]}, {"code": 232, "indent": 0, "parameters": [67, 0, 0, 0, 105, -50, 100, 100, 255, 0, 60, true]}, {"code": 230, "indent": 0, "parameters": [60]}, {"code": 111, "indent": 0, "parameters": [13, 0]}, {"code": 232, "indent": 1, "parameters": [70, 0, 0, 0, 0, 0, 100, 100, 0, 0, 80, true]}, {"code": 0, "indent": 1, "parameters": []}, {"code": 412, "indent": 0, "parameters": []}, {"code": 111, "indent": 0, "parameters": [0, 246, 0]}, {"code": 101, "indent": 1, "parameters": ["", 0, 1, 2]}, {"code": 401, "indent": 1, "parameters": ["После событий, произошедших в вашем родном городе,"]}, {"code": 401, "indent": 1, "parameters": ["оглядываться назад больше было нельзя."]}, {"code": 101, "indent": 1, "parameters": ["", 0, 1, 2]}, {"code": 401, "indent": 1, "parameters": ["Это было к лучшему. Вы были вынужден разорвать все свои связи с"]}, {"code": 401, "indent": 1, "parameters": ["прошлым. Это было освобождающе. Наконец-то вы были свободны."]}, {"code": 101, "indent": 1, "parameters": ["", 0, 1, 2]}, {"code": 401, "indent": 1, "parameters": ["...По крайней мере, так мне казалось в течение первых нескольких недель."]}, {"code": 401, "indent": 1, "parameters": ["Постепенно все, чему вы были свидетелями, начало давить на вас."]}, {"code": 101, "indent": 1, "parameters": ["", 0, 1, 2]}, {"code": 401, "indent": 1, "parameters": ["Чтобы отбросить все страдания и ужасы, вы переезжали с одного места на"]}, {"code": 401, "indent": 1, "parameters": ["другое. Никогда не пускает корни в какое-то определенное место. Всегда в"]}, {"code": 401, "indent": 1, "parameters": ["бегах, чтобы тебе не пришлось сталкиваться с прошлым..."]}, {"code": 101, "indent": 1, "parameters": ["", 0, 1, 2]}, {"code": 401, "indent": 1, "parameters": ["Вы приезжали в новый город, в новую страну, какое-то время выполняли"]}, {"code": 401, "indent": 1, "parameters": ["любую работу, которая у вас была, пока события \"Прехевила\" снова не"]}, {"code": 401, "indent": 1, "parameters": ["начали вторгаться в ваши кошмары."]}, {"code": 101, "indent": 1, "parameters": ["", 0, 1, 2]}, {"code": 401, "indent": 1, "parameters": ["Вот тогда-то ты и понял, что пришло время уходить еще раз."]}, {"code": 101, "indent": 1, "parameters": ["", 0, 1, 2]}, {"code": 401, "indent": 1, "parameters": ["Может быть, однажды ты зайдешь достаточно далеко, чтобы прошлое"]}, {"code": 401, "indent": 1, "parameters": ["больше не могло преследовать тебя ? Или, может быть, прошлое"]}, {"code": 401, "indent": 1, "parameters": ["наконец-то настигнет тебя?"]}, {"code": 0, "indent": 1, "parameters": []}, {"code": 411, "indent": 0, "parameters": []}, {"code": 111, "indent": 1, "parameters": [0, 242, 0]}, {"code": 101, "indent": 2, "parameters": ["", 0, 1, 2]}, {"code": 401, "indent": 2, "parameters": ["У тебя не осталось никакого бремени от твоей прежней жизни. Это было"]}, {"code": 401, "indent": 2, "parameters": ["горько -сладкое чувство. Ваши связи с вашей семьей и прошлым были"]}, {"code": 401, "indent": 2, "parameters": ["разорваны благодаря травмирующим событиям, произошедшим в"]}, {"code": 401, "indent": 2, "parameters": ["Прехевиле."]}, {"code": 101, "indent": 2, "parameters": ["", 0, 1, 2]}, {"code": 401, "indent": 2, "parameters": ["Мысль о возвращении в Ватикан для продолжения учебы"]}, {"code": 401, "indent": 2, "parameters": ["не казалась привлекательной. Не после всего, что ты видел. Некоторые"]}, {"code": 401, "indent": 2, "parameters": ["вещи не предназначались для того, чтобы люди вмешивались в них."]}, {"code": 101, "indent": 2, "parameters": ["", 0, 1, 2]}, {"code": 401, "indent": 2, "parameters": ["Шли годы, вы проделали весь путь до страны Валланд"]}, {"code": 401, "indent": 2, "parameters": ["и обнаружили, что обосновались в столичном районе красных фонарей."]}, {"code": 401, "indent": 2, "parameters": [""]}, {"code": 101, "indent": 2, "parameters": ["", 0, 1, 2]}, {"code": 401, "indent": 2, "parameters": ["У вас были проблемы с общением с обычными людьми, которые не знали о"]}, {"code": 401, "indent": 2, "parameters": ["более широком плане вещей, но у людей, населявших"]}, {"code": 401, "indent": 2, "parameters": ["район красных фонарей, вы нашли родственные души."]}, {"code": 101, "indent": 2, "parameters": ["", 0, 1, 2]}, {"code": 401, "indent": 2, "parameters": ["Все носили там багаж, и никто никого не осуждал."]}, {"code": 101, "indent": 2, "parameters": ["", 0, 1, 2]}, {"code": 401, "indent": 2, "parameters": ["Оккультные навыки помогали вам легко заводить друзей, и было много"]}, {"code": 401, "indent": 2, "parameters": ["способов заработать там на жизнь с помощью небольшой магии."]}, {"code": 101, "indent": 2, "parameters": ["", 0, 1, 2]}, {"code": 401, "indent": 2, "parameters": ["На самом деле все было довольно мило. Теперь, если бы вы только могли"]}, {"code": 401, "indent": 2, "parameters": ["сказать, кто был этот фотобомбировщик... Она пыталась подружиться с"]}, {"code": 401, "indent": 2, "parameters": ["тобой в течение самого долгого времени... Довольно раздражающий."]}, {"code": 0, "indent": 2, "parameters": []}, {"code": 411, "indent": 1, "parameters": []}, {"code": 111, "indent": 2, "parameters": [0, 243, 0]}, {"code": 101, "indent": 3, "parameters": ["", 0, 1, 2]}, {"code": 401, "indent": 3, "parameters": ["Что ж, это ничего не решило. Все это, а ты все еще ничего"]}, {"code": 401, "indent": 3, "parameters": ["не знал."]}, {"code": 101, "indent": 3, "parameters": ["", 0, 1, 2]}, {"code": 401, "indent": 3, "parameters": ["Мистические божества, неизвестные боги, нечестивые ритуалы... Крупицы"]}, {"code": 401, "indent": 3, "parameters": ["информации... Были ли ответы похоронены где-то среди всего этого"]}, {"code": 401, "indent": 3, "parameters": ["безумия?"]}, {"code": 101, "indent": 3, "parameters": ["", 0, 1, 2]}, {"code": 401, "indent": 3, "parameters": ["Будут ли ответы вообще иметь какое-то значение? Если барон фон Датч"]}, {"code": 401, "indent": 3, "parameters": ["запачкал свои руки кровью, то вы наслаждались кровавой баней по"]}, {"code": 401, "indent": 3, "parameters": ["сравнению с тем, чтобы оказаться там, где вы находитесь сейчас."]}, {"code": 101, "indent": 3, "parameters": ["", 0, 1, 2]}, {"code": 401, "indent": 3, "parameters": ["Ты слышишь тяжелые шаги этого злого кота. Он знает, что"]}, {"code": 401, "indent": 3, "parameters": ["ты сделал. В Прехевиле и раньше. Кошка кружит вокруг"]}, {"code": 401, "indent": 3, "parameters": ["вас в темноте. Просто за пределами вашей прямой видимости."]}, {"code": 101, "indent": 3, "parameters": ["", 0, 1, 2]}, {"code": 401, "indent": 3, "parameters": ["Может быть, тебе стоит просто принять его предложение? Что ещё тебе"]}, {"code": 401, "indent": 3, "parameters": ["остаётся?"]}, {"code": 101, "indent": 3, "parameters": ["", 0, 1, 2]}, {"code": 401, "indent": 3, "parameters": ["Ничего. Верно."]}, {"code": 101, "indent": 3, "parameters": ["", 0, 1, 2]}, {"code": 401, "indent": 3, "parameters": ["Это странно, не правда ли, старина? Жизнь, которая есть."]}, {"code": 0, "indent": 3, "parameters": []}, {"code": 411, "indent": 2, "parameters": []}, {"code": 111, "indent": 3, "parameters": [0, 244, 0]}, {"code": 101, "indent": 4, "parameters": ["", 0, 1, 2]}, {"code": 401, "indent": 4, "parameters": ["Вы не могли уснуть после того, чему стали свидетелями в Прехевиле."]}, {"code": 401, "indent": 4, "parameters": ["Ты слишком много знал о Вселенной и о том, какие ужасы она скрывает во"]}, {"code": 401, "indent": 4, "parameters": ["тьме ночи."]}, {"code": 101, "indent": 4, "parameters": ["", 0, 1, 2]}, {"code": 401, "indent": 4, "parameters": ["Бесконечная пустота наверху, в небе, насмехалась над тобой. Оно смеялось"]}, {"code": 401, "indent": 4, "parameters": ["над тобой. Вы, наконец, поняли, насколько на самом деле ничтожны люди"]}, {"code": 401, "indent": 4, "parameters": ["в великой схеме вещей."]}, {"code": 101, "indent": 4, "parameters": ["", 0, 1, 2]}, {"code": 401, "indent": 4, "parameters": ["Твоя бессонница чуть не свела тебя с ума. Но ты всегда был тем,"]}, {"code": 401, "indent": 4, "parameters": ["кто искал ответы и решения. Несомненно,"]}, {"code": 401, "indent": 4, "parameters": ["и здесь можно было найти ответ."]}, {"code": 101, "indent": 4, "parameters": ["", 0, 1, 2]}, {"code": 401, "indent": 4, "parameters": ["Луна нанесла тебе визит и посмотрела на тебя на короткую секунду. Чтобы"]}, {"code": 401, "indent": 4, "parameters": ["получить ответы, вам тоже нужно было бы нанести визит Богу Луны."]}, {"code": 101, "indent": 4, "parameters": ["", 0, 1, 2]}, {"code": 401, "indent": 4, "parameters": ["Вы занимали высокие посты в областях, которые изучали космические"]}, {"code": 401, "indent": 4, "parameters": ["технологии. С годами дела начали продвигаться вперед, и только через"]}, {"code": 401, "indent": 4, "parameters": ["десять лет вы уже готовились запускать людей на Луну."]}, {"code": 101, "indent": 4, "parameters": ["", 0, 1, 2]}, {"code": 401, "indent": 4, "parameters": ["Скоро ты получишь аудиенцию у Луны. Не с помощью древних ритуалов"]}, {"code": 401, "indent": 4, "parameters": ["или оккультизма, а благодаря технологиям и человеческому уму."]}, {"code": 101, "indent": 4, "parameters": ["", 0, 1, 2]}, {"code": 401, "indent": 4, "parameters": ["Была ли это хорошая идея, еще предстоит выяснить..."]}, {"code": 0, "indent": 4, "parameters": []}, {"code": 411, "indent": 3, "parameters": []}, {"code": 111, "indent": 4, "parameters": [0, 2401, 0]}, {"code": 101, "indent": 5, "parameters": ["", 0, 1, 2]}, {"code": 401, "indent": 5, "parameters": ["Культ серы... последователи Рхера... церковь"]}, {"code": 401, "indent": 5, "parameters": ["Алл-мера... Отличались ли они чем-нибудь от желтых магов?"]}, {"code": 101, "indent": 5, "parameters": ["", 0, 1, 2]}, {"code": 401, "indent": 5, "parameters": ["В конечном счете все они служили кому-то другому. Твой хозяин просто"]}, {"code": 401, "indent": 5, "parameters": ["оказался сквернословящим старым изюмом, о котором время забыло."]}, {"code": 101, "indent": 5, "parameters": ["", 0, 1, 2]}, {"code": 401, "indent": 5, "parameters": ["Ты сбросил своего хозяина в ближайшее озеро. Может быть, какой-нибудь"]}, {"code": 401, "indent": 5, "parameters": ["бедняга найдет его там столетия спустя, и его поведут, как дурака на"]}, {"code": 401, "indent": 5, "parameters": ["поводке, выполнять приказы своего хозяина. Но это больше не было твоей"]}, {"code": 401, "indent": 5, "parameters": ["частью."]}, {"code": 101, "indent": 5, "parameters": ["", 0, 1, 2]}, {"code": 401, "indent": 5, "parameters": ["Ты вернулся в Абиссинию, на свою родину."]}, {"code": 101, "indent": 5, "parameters": ["", 0, 1, 2]}, {"code": 401, "indent": 5, "parameters": ["Причина, по которой вы изначально покинули весь континент,"]}, {"code": 401, "indent": 5, "parameters": ["заключалась в состоянии религии и поклонения там. Учения о Алл-мер"]}, {"code": 401, "indent": 5, "parameters": ["перенял старые верования."]}, {"code": 101, "indent": 5, "parameters": ["", 0, 1, 2]}, {"code": 401, "indent": 5, "parameters": ["Во время своих путешествий вы накопили достаточно знаний и навыков,"]}, {"code": 401, "indent": 5, "parameters": ["чтобы соперничать с тем, что продвигали местные храмы."]}, {"code": 101, "indent": 5, "parameters": ["", 0, 1, 2]}, {"code": 401, "indent": 5, "parameters": ["Эти земли будут следовать вашим учениям в будущем. Учения,"]}, {"code": 401, "indent": 5, "parameters": ["которые принесли бы пользу тем, кто практикует ваш путь. Ни те, кто"]}, {"code": 401, "indent": 5, "parameters": ["находится у власти, ни истеблишмент."]}, {"code": 101, "indent": 5, "parameters": ["", 0, 1, 2]}, {"code": 401, "indent": 5, "parameters": ["Кого-то можно было почти одурачить, заставив подумать, что это был"]}, {"code": 401, "indent": 5, "parameters": ["альтруистический поступок. Конечно, в манере истинного желтого мага на"]}, {"code": 401, "indent": 5, "parameters": ["этот раз ты был бы на вершине пирамиды."]}, {"code": 0, "indent": 5, "parameters": []}, {"code": 411, "indent": 4, "parameters": []}, {"code": 111, "indent": 5, "parameters": [0, 2402, 0]}, {"code": 101, "indent": 6, "parameters": ["", 0, 1, 2]}, {"code": 401, "indent": 6, "parameters": ["Что-то хорошее действительно произошло из вашего травматического"]}, {"code": 401, "indent": 6, "parameters": ["опыта в Прехевиле. Потребовались годы терапии, чтобы осознать это, но"]}, {"code": 401, "indent": 6, "parameters": ["постепенно вы поняли, на что вы действительно способны."]}, {"code": 101, "indent": 6, "parameters": ["", 0, 1, 2]}, {"code": 401, "indent": 6, "parameters": ["Ты была чемпионом Термины. Ты. В cвоем инвалидном кресле и другими"]}, {"code": 401, "indent": 6, "parameters": ["недугами. Каким-то образом ты оказалась единственным выжившим в том,"]}, {"code": 401, "indent": 6, "parameters": ["что произошло в этом забытом богом захолустном городке."]}, {"code": 101, "indent": 6, "parameters": ["", 0, 1, 2]}, {"code": 401, "indent": 6, "parameters": ["С годами ты также начала чувствовать дух своей сестры."]}, {"code": 401, "indent": 6, "parameters": ["Она сопровождала тебя везде, куда бы ты ни пошла."]}, {"code": 101, "indent": 6, "parameters": ["", 0, 1, 2]}, {"code": 401, "indent": 6, "parameters": ["Ты никогда до конца не понимала, что с ней случилось, но она следовала за"]}, {"code": 401, "indent": 6, "parameters": ["тобой на каждом шагу с тех пор, как вы двое покинули этот порочный"]}, {"code": 401, "indent": 6, "parameters": ["город."]}, {"code": 101, "indent": 6, "parameters": ["", 0, 1, 2]}, {"code": 401, "indent": 6, "parameters": ["Ты обрела мужество и уверенность в себе после этого испытания. С этой"]}, {"code": 401, "indent": 6, "parameters": ["вновь обретенной уверенностью ты отправилась в самые отдаленные"]}, {"code": 401, "indent": 6, "parameters": ["уголки мира, чтобы изучать их флору и фауну."]}, {"code": 101, "indent": 6, "parameters": ["", 0, 1, 2]}, {"code": 401, "indent": 6, "parameters": ["Вы узнали, что природа заботится о вас независимо от того, куда"]}, {"code": 401, "indent": 6, "parameters": ["вы идете. У тебя больше не было ограничений человеческого тела."]}, {"code": 101, "indent": 6, "parameters": ["", 0, 1, 2]}, {"code": 401, "indent": 6, "parameters": ["Впервые в своей жизни вы почувствовали настоящую свободу."]}, {"code": 0, "indent": 6, "parameters": []}, {"code": 411, "indent": 5, "parameters": []}, {"code": 111, "indent": 6, "parameters": [0, 2403, 0]}, {"code": 101, "indent": 7, "parameters": ["", 0, 1, 2]}, {"code": 401, "indent": 7, "parameters": ["Город Прехевил должен был стать всего лишь ступенькой на вашем пути к"]}, {"code": 401, "indent": 7, "parameters": ["более зеленым пастбищам. Вместо этого это оказалось местом, которое"]}, {"code": 401, "indent": 7, "parameters": ["сформировало того самого человека, которым вы в конечном итоге стали."]}, {"code": 101, "indent": 7, "parameters": ["", 0, 1, 2]}, {"code": 401, "indent": 7, "parameters": ["Твоя сестра ждала тебя в Королевстве Рондон, таков был"]}, {"code": 401, "indent": 7, "parameters": ["план. Она приветствовала вас, не подозревая об ужасах,"]}, {"code": 401, "indent": 7, "parameters": ["свидетелями которых вы были по пути туда."]}, {"code": 101, "indent": 7, "parameters": ["", 0, 1, 2]}, {"code": 401, "indent": 7, "parameters": ["Вы никогда не говорили о своих переживаниях, даже если эти события"]}, {"code": 401, "indent": 7, "parameters": ["поглощали вас каждую ночь, когда вы ложились спать."]}, {"code": 101, "indent": 7, "parameters": ["", 0, 1, 2]}, {"code": 401, "indent": 7, "parameters": ["Люди каждый день ходили по улицам Рондона, не зная, что"]}, {"code": 401, "indent": 7, "parameters": ["скрывается в тени каждого темного уголка мира."]}, {"code": 101, "indent": 7, "parameters": ["", 0, 1, 2]}, {"code": 401, "indent": 7, "parameters": ["Так было лучше. Было лучше, что они не знали, насколько они на самом"]}, {"code": 401, "indent": 7, "parameters": ["деле беспомощны перед космическими ужасами снаружи. Но вы могли бы"]}, {"code": 401, "indent": 7, "parameters": ["помочь им подготовиться, если бы им когда-нибудь пришлось столкнуться"]}, {"code": 401, "indent": 7, "parameters": ["лицом к лицу с чем-либо подобного рода."]}, {"code": 101, "indent": 7, "parameters": ["", 0, 1, 2]}, {"code": 401, "indent": 7, "parameters": ["Вы начали руководить боксерским залом с вашим опытом. Посетители"]}, {"code": 401, "indent": 7, "parameters": ["заходили внутрь в надежде научиться защищаться от обычных уличных"]}, {"code": 401, "indent": 7, "parameters": ["головорезов, но они выходили наружу, готовые встретиться лицом к лицу с"]}, {"code": 401, "indent": 7, "parameters": ["неизвестностью."]}, {"code": 101, "indent": 7, "parameters": ["", 0, 1, 2]}, {"code": 401, "indent": 7, "parameters": ["Подобное спасение человеческих жизней даже отчасти смягчило твою"]}, {"code": 401, "indent": 7, "parameters": ["внутреннюю вину. Ты отнял жизни у многих, но, возможно, ты мог"]}, {"code": 401, "indent": 7, "parameters": ["бы наконец и что-то вернуть."]}, {"code": 0, "indent": 7, "parameters": []}, {"code": 411, "indent": 6, "parameters": []}, {"code": 111, "indent": 7, "parameters": [0, 2404, 0]}, {"code": 101, "indent": 8, "parameters": ["", 0, 1, 2]}, {"code": 401, "indent": 8, "parameters": ["События Прехевила потрясли вас до глубины души. Внезапно многие"]}, {"code": 401, "indent": 8, "parameters": ["вещи в жизни показались бессмысленными на фоне этого ошеломляющего"]}, {"code": 401, "indent": 8, "parameters": ["осознания того, что скрывается за завесой между известным и"]}, {"code": 401, "indent": 8, "parameters": ["неизвестным."]}, {"code": 101, "indent": 8, "parameters": ["", 0, 1, 2]}, {"code": 401, "indent": 8, "parameters": ["Вернувшись обратно к цивилизации, вы поняли, что ваши переживания"]}, {"code": 401, "indent": 8, "parameters": ["прозвучали бы как бред сумасшедшего, если бы вы когда-нибудь"]}, {"code": 401, "indent": 8, "parameters": ["попытались изложить их на бумаге."]}, {"code": 101, "indent": 8, "parameters": ["", 0, 1, 2]}, {"code": 401, "indent": 8, "parameters": ["Тебе нужны были доказательства, прежде чем ты смог открыть рот. Вы"]}, {"code": 401, "indent": 8, "parameters": ["были свидетелями слухов о Новых богах и Кайзере в реальной жизни. Ты"]}, {"code": 401, "indent": 8, "parameters": ["знал, что они настоящие."]}, {"code": 101, "indent": 8, "parameters": ["", 0, 1, 2]}, {"code": 401, "indent": 8, "parameters": ["Это уже было половиной работы. Теперь вам оставалось только убедить"]}, {"code": 401, "indent": 8, "parameters": ["остальной мир в этой запрещенной информации."]}, {"code": 101, "indent": 8, "parameters": ["", 0, 1, 2]}, {"code": 401, "indent": 8, "parameters": ["Эта цель помогала вам справляться с каждым днем. Вам нужны были"]}, {"code": 401, "indent": 8, "parameters": ["четкие цели, чтобы изгнать страх из вашего разума."]}, {"code": 101, "indent": 8, "parameters": ["", 0, 1, 2]}, {"code": 401, "indent": 8, "parameters": ["Вы начали копать. Как ты всегда делал. Рано или поздно вы"]}, {"code": 401, "indent": 8, "parameters": ["добрались бы до корня вещей. Еще неизвестно, выдержит ли ваше"]}, {"code": 401, "indent": 8, "parameters": ["здравомыслие правду или нет..."]}, {"code": 0, "indent": 8, "parameters": []}, {"code": 412, "indent": 7, "parameters": []}, {"code": 0, "indent": 7, "parameters": []}, {"code": 412, "indent": 6, "parameters": []}, {"code": 0, "indent": 6, "parameters": []}, {"code": 412, "indent": 5, "parameters": []}, {"code": 0, "indent": 5, "parameters": []}, {"code": 412, "indent": 4, "parameters": []}, {"code": 0, "indent": 4, "parameters": []}, {"code": 412, "indent": 3, "parameters": []}, {"code": 0, "indent": 3, "parameters": []}, {"code": 412, "indent": 2, "parameters": []}, {"code": 0, "indent": 2, "parameters": []}, {"code": 412, "indent": 1, "parameters": []}, {"code": 0, "indent": 1, "parameters": []}, {"code": 412, "indent": 0, "parameters": []}, {"code": 230, "indent": 0, "parameters": [80]}, {"code": 123, "indent": 0, "parameters": ["A", 0]}, {"code": 0, "indent": 0, "parameters": []}], "moveFrequency": 2, "moveRoute": {"list": [{"code": 0, "parameters": []}], "repeat": true, "skippable": false, "wait": false}, "moveSpeed": 2, "moveType": 0, "priorityType": 0, "stepAnime": false, "through": false, "trigger": 3, "walkAnime": true}, {"conditions": {"actorId": 1, "actorValid": false, "itemId": 1, "itemValid": false, "selfSwitchCh": "A", "selfSwitchValid": true, "switch1Id": 1, "switch1Valid": false, "switch2Id": 1, "switch2Valid": false, "variableId": 1, "variableValid": false, "variableValue": 0}, "directionFix": false, "image": {"characterIndex": 0, "characterName": "", "direction": 2, "pattern": 0, "tileId": 0}, "list": [{"code": 108, "indent": 0, "parameters": ["UNLOCKABLES"]}, {"code": 230, "indent": 0, "parameters": [60]}, {"code": 111, "indent": 0, "parameters": [1, 1388, 0, 1, 1]}, {"code": 108, "indent": 1, "parameters": ["ENDING B"]}, {"code": 111, "indent": 1, "parameters": [0, 1439, 1]}, {"code": 121, "indent": 2, "parameters": [1439, 1439, 0]}, {"code": 250, "indent": 2, "parameters": [{"name": "clock_ring2_409033__helterskelter1114__old-clock-ring_01", "volume": 90, "pitch": 100, "pan": 0}]}, {"code": 101, "indent": 2, "parameters": ["", 0, 1, 1]}, {"code": 401, "indent": 2, "parameters": ["\\i[9]\\}ЛУННЫЙ МЕТЕОРИТ\\{ теперь доступен в хексен!"]}, {"code": 230, "indent": 2, "parameters": [40]}, {"code": 0, "indent": 2, "parameters": []}, {"code": 412, "indent": 1, "parameters": []}, {"code": 111, "indent": 1, "parameters": [0, 4819, 0]}, {"code": 111, "indent": 2, "parameters": [0, 1436, 1]}, {"code": 121, "indent": 3, "parameters": [1436, 1436, 0]}, {"code": 250, "indent": 3, "parameters": [{"name": "clock_ring2_409033__helterskelter1114__old-clock-ring_01", "volume": 90, "pitch": 100, "pan": 0}]}, {"code": 101, "indent": 3, "parameters": ["", 0, 1, 1]}, {"code": 401, "indent": 3, "parameters": ["\\i[9]\\}ЛУННЫЙ ШТОРМ\\{ теперь доступен в хексен!"]}, {"code": 230, "indent": 3, "parameters": [40]}, {"code": 0, "indent": 3, "parameters": []}, {"code": 412, "indent": 2, "parameters": []}, {"code": 0, "indent": 2, "parameters": []}, {"code": 412, "indent": 1, "parameters": []}, {"code": 0, "indent": 1, "parameters": []}, {"code": 411, "indent": 0, "parameters": []}, {"code": 111, "indent": 1, "parameters": [1, 1389, 0, 1, 1]}, {"code": 111, "indent": 2, "parameters": [0, 1438, 1]}, {"code": 121, "indent": 3, "parameters": [1438, 1438, 0]}, {"code": 250, "indent": 3, "parameters": [{"name": "clock_ring2_409033__helterskelter1114__old-clock-ring_01", "volume": 90, "pitch": 100, "pan": 0}]}, {"code": 101, "indent": 3, "parameters": ["", 0, 1, 1]}, {"code": 401, "indent": 3, "parameters": ["\\i[344]\\}ЛОНГИН\\{ теперь доступен в хексен!"]}, {"code": 230, "indent": 3, "parameters": [40]}, {"code": 0, "indent": 3, "parameters": []}, {"code": 412, "indent": 2, "parameters": []}, {"code": 0, "indent": 2, "parameters": []}, {"code": 411, "indent": 1, "parameters": []}, {"code": 111, "indent": 2, "parameters": [1, 1814, 0, 1, 1]}, {"code": 108, "indent": 3, "parameters": ["ENDING A"]}, {"code": 111, "indent": 3, "parameters": [0, 1440, 1]}, {"code": 121, "indent": 4, "parameters": [1440, 1440, 0]}, {"code": 250, "indent": 4, "parameters": [{"name": "clock_ring2_409033__helterskelter1114__old-clock-ring_01", "volume": 90, "pitch": 100, "pan": 0}]}, {"code": 101, "indent": 4, "parameters": ["", 0, 1, 1]}, {"code": 401, "indent": 4, "parameters": ["\\i[345]\\}КРАСНАЯ ДУГА\\{ теперь доступна в хексен!"]}, {"code": 230, "indent": 4, "parameters": [40]}, {"code": 0, "indent": 4, "parameters": []}, {"code": 412, "indent": 3, "parameters": []}, {"code": 111, "indent": 3, "parameters": [0, 4819, 0]}, {"code": 111, "indent": 4, "parameters": [0, 1437, 1]}, {"code": 121, "indent": 5, "parameters": [1437, 1437, 0]}, {"code": 250, "indent": 5, "parameters": [{"name": "clock_ring2_409033__helterskelter1114__old-clock-ring_01", "volume": 90, "pitch": 100, "pan": 0}]}, {"code": 101, "indent": 5, "parameters": ["", 0, 1, 1]}, {"code": 401, "indent": 5, "parameters": ["\\i[345]\\}РОЙ МОТЫЛЬКОВ\\{ теперь доступен в хексен!"]}, {"code": 230, "indent": 5, "parameters": [40]}, {"code": 0, "indent": 5, "parameters": []}, {"code": 412, "indent": 4, "parameters": []}, {"code": 0, "indent": 4, "parameters": []}, {"code": 412, "indent": 3, "parameters": []}, {"code": 0, "indent": 3, "parameters": []}, {"code": 412, "indent": 2, "parameters": []}, {"code": 0, "indent": 2, "parameters": []}, {"code": 412, "indent": 1, "parameters": []}, {"code": 0, "indent": 1, "parameters": []}, {"code": 412, "indent": 0, "parameters": []}, {"code": 123, "indent": 0, "parameters": ["B", 0]}, {"code": 0, "indent": 0, "parameters": []}], "moveFrequency": 3, "moveRoute": {"list": [{"code": 0, "parameters": []}], "repeat": true, "skippable": false, "wait": false}, "moveSpeed": 3, "moveType": 0, "priorityType": 0, "stepAnime": false, "through": false, "trigger": 3, "walkAnime": true}, {"conditions": {"actorId": 1, "actorValid": false, "itemId": 1, "itemValid": false, "selfSwitchCh": "B", "selfSwitchValid": true, "switch1Id": 1, "switch1Valid": false, "switch2Id": 1, "switch2Valid": false, "variableId": 1, "variableValid": false, "variableValue": 0}, "directionFix": false, "image": {"characterIndex": 0, "characterName": "", "direction": 2, "pattern": 0, "tileId": 0}, "list": [{"code": 230, "indent": 0, "parameters": [70]}, {"code": 231, "indent": 0, "parameters": [68, "black1", 0, 0, 25, 0, 120, 120, 0, 0]}, {"code": 232, "indent": 0, "parameters": [68, 0, 0, 0, 25, 0, 120, 120, 190, 0, 100, false]}, {"code": 108, "indent": 0, "parameters": ["CREDITS"]}, {"code": 117, "indent": 0, "parameters": [561]}, {"code": 232, "indent": 0, "parameters": [68, 0, 0, 0, 25, 0, 120, 120, 0, 0, 60, true]}, {"code": 123, "indent": 0, "parameters": ["C", 0]}, {"code": 0, "indent": 0, "parameters": []}], "moveFrequency": 3, "moveRoute": {"list": [{"code": 0, "parameters": []}], "repeat": true, "skippable": false, "wait": false}, "moveSpeed": 3, "moveType": 0, "priorityType": 0, "stepAnime": false, "through": false, "trigger": 3, "walkAnime": true}, {"conditions": {"actorId": 1, "actorValid": false, "itemId": 1, "itemValid": false, "selfSwitchCh": "C", "selfSwitchValid": true, "switch1Id": 1, "switch1Valid": false, "switch2Id": 1, "switch2Valid": false, "variableId": 1, "variableValid": false, "variableValue": 0}, "directionFix": false, "image": {"characterIndex": 0, "characterName": "", "direction": 2, "pattern": 0, "tileId": 0}, "list": [{"code": 111, "indent": 0, "parameters": [0, 246, 0]}, {"code": 101, "indent": 1, "parameters": ["", 0, 1, 1]}, {"code": 401, "indent": 1, "parameters": ["Спасибо вам за игру \\n[1]!"]}, {"code": 0, "indent": 1, "parameters": []}, {"code": 411, "indent": 0, "parameters": []}, {"code": 111, "indent": 1, "parameters": [0, 242, 0]}, {"code": 101, "indent": 2, "parameters": ["", 0, 1, 1]}, {"code": 401, "indent": 2, "parameters": ["Спасибо вам за игру \\n[3]!"]}, {"code": 0, "indent": 2, "parameters": []}, {"code": 411, "indent": 1, "parameters": []}, {"code": 111, "indent": 2, "parameters": [0, 243, 0]}, {"code": 101, "indent": 3, "parameters": ["", 0, 1, 1]}, {"code": 401, "indent": 3, "parameters": ["Спасибо вам за игру \\n[4]!"]}, {"code": 0, "indent": 3, "parameters": []}, {"code": 411, "indent": 2, "parameters": []}, {"code": 111, "indent": 3, "parameters": [0, 244, 0]}, {"code": 101, "indent": 4, "parameters": ["", 0, 1, 1]}, {"code": 401, "indent": 4, "parameters": ["Спасибо вам за игру \\n[5]!"]}, {"code": 0, "indent": 4, "parameters": []}, {"code": 411, "indent": 3, "parameters": []}, {"code": 111, "indent": 4, "parameters": [0, 2401, 0]}, {"code": 101, "indent": 5, "parameters": ["", 0, 1, 1]}, {"code": 401, "indent": 5, "parameters": ["Спасибо вам за игру \\n[6]!"]}, {"code": 0, "indent": 5, "parameters": []}, {"code": 411, "indent": 4, "parameters": []}, {"code": 111, "indent": 5, "parameters": [0, 2402, 0]}, {"code": 101, "indent": 6, "parameters": ["", 0, 1, 1]}, {"code": 401, "indent": 6, "parameters": ["Спасибо вам за игру \\n[15]!"]}, {"code": 0, "indent": 6, "parameters": []}, {"code": 411, "indent": 5, "parameters": []}, {"code": 111, "indent": 6, "parameters": [0, 2403, 0]}, {"code": 101, "indent": 7, "parameters": ["", 0, 1, 1]}, {"code": 401, "indent": 7, "parameters": ["Спасибо вам за игру \\n[13]!"]}, {"code": 0, "indent": 7, "parameters": []}, {"code": 411, "indent": 6, "parameters": []}, {"code": 111, "indent": 7, "parameters": [0, 2404, 0]}, {"code": 101, "indent": 8, "parameters": ["", 0, 1, 1]}, {"code": 401, "indent": 8, "parameters": ["Спасибо вам за игру \\n[14]!"]}, {"code": 0, "indent": 8, "parameters": []}, {"code": 411, "indent": 7, "parameters": []}, {"code": 101, "indent": 8, "parameters": ["", 0, 1, 1]}, {"code": 401, "indent": 8, "parameters": ["Спасибо вам за игру!"]}, {"code": 0, "indent": 8, "parameters": []}, {"code": 412, "indent": 7, "parameters": []}, {"code": 0, "indent": 7, "parameters": []}, {"code": 412, "indent": 6, "parameters": []}, {"code": 0, "indent": 6, "parameters": []}, {"code": 412, "indent": 5, "parameters": []}, {"code": 0, "indent": 5, "parameters": []}, {"code": 412, "indent": 4, "parameters": []}, {"code": 0, "indent": 4, "parameters": []}, {"code": 412, "indent": 3, "parameters": []}, {"code": 0, "indent": 3, "parameters": []}, {"code": 412, "indent": 2, "parameters": []}, {"code": 0, "indent": 2, "parameters": []}, {"code": 412, "indent": 1, "parameters": []}, {"code": 0, "indent": 1, "parameters": []}, {"code": 412, "indent": 0, "parameters": []}, {"code": 230, "indent": 0, "parameters": [80]}, {"code": 242, "indent": 0, "parameters": [3]}, {"code": 232, "indent": 0, "parameters": [70, 0, 0, 0, 0, 0, 100, 100, 255, 0, 180, true]}, {"code": 223, "indent": 0, "parameters": [[-255, -255, -255, 0], 160, false]}, {"code": 353, "indent": 0, "parameters": []}, {"code": 0, "indent": 0, "parameters": []}], "moveFrequency": 3, "moveRoute": {"list": [{"code": 0, "parameters": []}], "repeat": true, "skippable": false, "wait": false}, "moveSpeed": 3, "moveType": 0, "priorityType": 0, "stepAnime": false, "through": false, "trigger": 3, "walkAnime": true}], "x": 2, "y": 5}, {"id": 2, "name": "EV002", "note": "", "pages": [{"conditions": {"actorId": 1, "actorValid": false, "itemId": 1, "itemValid": false, "selfSwitchCh": "A", "selfSwitchValid": false, "switch1Id": 1, "switch1Valid": false, "switch2Id": 1, "switch2Valid": false, "variableId": 1, "variableValid": false, "variableValue": 0}, "directionFix": false, "image": {"characterIndex": 0, "characterName": "", "direction": 2, "pattern": 0, "tileId": 0}, "list": [{"code": 0, "indent": 0, "parameters": []}], "moveFrequency": 3, "moveRoute": {"list": [{"code": 0, "parameters": []}], "repeat": true, "skippable": false, "wait": false}, "moveSpeed": 3, "moveType": 0, "priorityType": 1, "stepAnime": false, "through": false, "trigger": 0, "walkAnime": true}], "x": 4, "y": 5}, {"id": 3, "name": "EV003", "note": "", "pages": [{"conditions": {"actorId": 1, "actorValid": false, "itemId": 1, "itemValid": false, "selfSwitchCh": "A", "selfSwitchValid": false, "switch1Id": 1, "switch1Valid": false, "switch2Id": 1, "switch2Valid": false, "variableId": 1, "variableValid": false, "variableValue": 0}, "directionFix": false, "image": {"characterIndex": 0, "characterName": "", "direction": 2, "pattern": 0, "tileId": 0}, "list": [{"code": 0, "indent": 0, "parameters": []}], "moveFrequency": 3, "moveRoute": {"list": [{"code": 0, "parameters": []}], "repeat": true, "skippable": false, "wait": false}, "moveSpeed": 3, "moveType": 0, "priorityType": 1, "stepAnime": false, "through": false, "trigger": 0, "walkAnime": true}], "x": 5, "y": 4}, {"id": 4, "name": "EV004", "note": "", "pages": [{"conditions": {"actorId": 1, "actorValid": false, "itemId": 1, "itemValid": false, "selfSwitchCh": "A", "selfSwitchValid": false, "switch1Id": 1, "switch1Valid": false, "switch2Id": 1, "switch2Valid": false, "variableId": 1, "variableValid": false, "variableValue": 0}, "directionFix": false, "image": {"characterIndex": 0, "characterName": "", "direction": 2, "pattern": 0, "tileId": 0}, "list": [{"code": 0, "indent": 0, "parameters": []}], "moveFrequency": 3, "moveRoute": {"list": [{"code": 0, "parameters": []}], "repeat": true, "skippable": false, "wait": false}, "moveSpeed": 3, "moveType": 0, "priorityType": 1, "stepAnime": false, "through": false, "trigger": 0, "walkAnime": true}], "x": 5, "y": 6}, {"id": 5, "name": "EV005", "note": "", "pages": [{"conditions": {"actorId": 1, "actorValid": false, "itemId": 1, "itemValid": false, "selfSwitchCh": "A", "selfSwitchValid": false, "switch1Id": 1, "switch1Valid": false, "switch2Id": 1, "switch2Valid": false, "variableId": 1, "variableValid": false, "variableValue": 0}, "directionFix": false, "image": {"characterIndex": 0, "characterName": "", "direction": 2, "pattern": 0, "tileId": 0}, "list": [{"code": 0, "indent": 0, "parameters": []}], "moveFrequency": 3, "moveRoute": {"list": [{"code": 0, "parameters": []}], "repeat": true, "skippable": false, "wait": false}, "moveSpeed": 3, "moveType": 0, "priorityType": 1, "stepAnime": false, "through": false, "trigger": 0, "walkAnime": true}], "x": 6, "y": 5}, null, null]}